{"txn_id":"TXN-11044","cust_id":6439968092,"amount":8871.15,"points":3,"is_member":false,"status":"COMPLETED","txn_date":"2026-02-10 04:32:12"}
{"txn_id":"TXN-14844","cust_id":7245991553,"amount":12316.36,"points":27,"is_member":false,"status":"PENDING","txn_date":"2026-02-10 06:33:04"}
{"txn_id":"TXN-24319","cust_id":6904500237,"amount":7359.8,"points":59,"is_member":true,"status":"COMPLETED","txn_date":"2026-02-10 07:57:42"}
{"txn_id":"TXN-26132","cust_id":2213569454,"amount":7456.38,"points":366,"is_member":true,"status":"COMPLETED","txn_date":"2026-02-10 18:51:40"}
{"txn_id":"TXN-27864","cust_id":3878529472,"amount":8611.96,"points":265,"is_member":false,"status":"CANCELLED","txn_date":"2026-02-10 09:11:10"}
{"txn_id":"TXN-29878","cust_id":6904500237,"amount":3286.08,"points":489,"is_member":false,"status":"COMPLETED","txn_date":"2026-02-10 14:09:04"}
{"txn_id":"TXN-31838","cust_id":5828340170,"amount":10559.13,"points":480,"is_member":true,"status":"CANCELLED","txn_date":"2026-02-10 14:36:26"}
{"txn_id":"TXN-35301","cust_id":4474717052,"points":485,"is_member":true,"status":"COMPLETED","txn_date":"2026-02-10 14:00:37"}
{"txn_id":"TXN-36739","cust_id":7245991553,"amount":11193.72,"points":273,"is_member":false,"status":"PENDING","txn_date":"2026-02-10 13:31:47"}
{"txn_id":"TXN-40643","cust_id":4568329534,"amount":5653.98,"points":409,"is_member":false,"status":"PENDING","txn_date":"2026-02-10 09:52:11"}
{"txn_id":"TXN-41787","cust_id":4351630478,"points":219,"is_member":false,"status":"COMPLETED","txn_date":"2026-02-10 09:53:06"}
{"txn_id":"TXN-46400","cust_id":3991308074,"amount":10767.31,"points":222,"is_member":true,"status":"CANCELLED","txn_date":"2026-02-10 17:00:36"}
{"txn_id":"TXN-49316","cust_id":8716952983,"amount":899.44,"points":236,"is_member":true,"status":"PENDING","txn_date":"2026-02-10 14:43:21"}
{"txn_id":"TXN-54317","cust_id":3991308074,"amount":5729.17,"points":428,"is_member":false,"status":"COMPLETED","txn_date":"2026-02-10 21:13:36"}
{"txn_id":"TXN-58521","cust_id":7651565215,"amount":202.68,"points":478,"is_member":true,"status":"PENDING","txn_date":"2026-02-10 10:29:34"}
{"txn_id":"TXN-62656","cust_id":8148109337,"amount":6300.26,"points":410,"is_member":true,"status":"COMPLETED","txn_date":"2026-02-10 01:02:09"}
{"txn_id":"TXN-65474","cust_id":3991308074,"amount":12088.38,"points":186,"is_member":false,"status":"COMPLETED","txn_date":"2026-02-10 03:15:38"}
{"txn_id":"TXN-72145","cust_id":6579398125,"points":13,"is_member":false,"status":"COMPLETED","txn_date":"2026-02-10 06:34:46"}
{"txn_id":"TXN-75193","cust_id":4058611172,"amount":4526.55,"points":18,"is_member":false,"status":"COMPLETED","txn_date":"2026-02-10 13:20:17"}
{"txn_id":"TXN-78243","cust_id":1474792354,"amount":10652.06,"points":263,"is_member":true,"status":"CANCELLED","txn_date":"2026-02-10 14:30:47"}
{"txn_id":"TXN-82190","cust_id":8716952983,"amount":12253.1,"points":486,"is_member":false,"status":"PENDING","txn_date":"2026-02-10 06:28:26"}
{"txn_id":"TXN-85561","cust_id":5285552918,"amount":11101.02,"points":413,"is_member":false,"status":"COMPLETED","txn_date":"2026-02-10 18:06:47"}
{"txn_id":"TXN-88737","cust_id":1674513681,"amount":12709.79,"points":431,"is_member":false,"status":"CANCELLED","txn_date":"2026-02-10 18:44:39"}
{"txn_id":"TXN-91934","cust_id":8871159003,"amount":319.89,"points":195,"is_member":false,"status":"CANCELLED","txn_date":"2026-02-10 20:51:58"}
{"txn_id":"TXN-96352","cust_id":1284364112,"points":476,"is_member":false,"status":"CANCELLED","txn_date":"2026-02-10 17:32:31"}
{"txn_id":"TXN-10662","cust_id":8913571312,"amount":5026.49,"points":15,"is_member":true,"status":"PENDING","txn_date":"2026-02-10 11:11:04"}
{"txn_id":"TXN-13982","cust_id":2712293212,"amount":10801.62,"points":179,"is_member":false,"status":"CANCELLED","txn_date":"2026-02-10 03:12:40"}
{"txn_id":"TXN-19617","cust_id":3878529472,"amount":12802.66,"points":137,"is_member":true,"status":"CANCELLED","txn_date":"2026-02-10 15:44:39"}
{"txn_id":"TXN-22088","cust_id":6904500237,"amount":10095.3,"points":191,"is_member":true,"status":"CANCELLED","txn_date":"2026-02-10 21:36:59"}
{"txn_id":"TXN-27616","cust_id":6904500237,"amount":11177.7,"points":209,"is_member":false,"status":"CANCELLED","txn_date":"2026-02-10 10:22:14"}
{"txn_id":"TXN-30920","cust_id":2213569454,"amount":627.08,"points":260,"is_member":true,"status":"COMPLETED","txn_date":"2026-02-10 07:42:56"}
{"txn_id":"TXN-34101","cust_id":1674513681,"amount":4531.38,"points":421,"is_member":true,"status":"PENDING","txn_date":"2026-02-10 05:15:12"}
{"txn_id":"TXN-35698","cust_id":7651565215,"amount":10359.12,"points":94,"is_member":false,"status":"CANCELLED","txn_date":"2026-02-10 09:28:25"}
{"txn_id":"TXN-40334","cust_id":9200954899,"amount":11964.19,"points":160,"is_member":true,"status":"CANCELLED","txn_date":"2026-02-10 11:23:47"}
{"txn_id":"TXN-44390","cust_id":7245991553,"amount":11787.57,"points":24,"is_member":true,"status":"PENDING","txn_date":"2026-02-10 20:35:53"}
{"txn_id":"TXN-47790","cust_id":2213569454,"amount":6749.81,"points":172,"is_member":true,"status":"COMPLETED","txn_date":"2026-02-10 05:05:17"}
{"txn_id":"TXN-51667","cust_id":5285552918,"amount":12998.2,"points":115,"is_member":false,"status":"PENDING","txn_date":"2026-02-10 22:28:53"}
{"txn_id":"TXN-54215","cust_id":5285552918,"amount":13914.24,"points":147,"is_member":true,"status":"CANCELLED","txn_date":"2026-02-10 21:09:31"}
{"txn_id":"TXN-56943","cust_id":9200954899,"amount":13772.58,"points":498,"is_member":false,"status":"PENDING","txn_date":"2026-02-10 01:57:48"}
{"txn_id":"TXN-61266","cust_id":1539140569,"amount":12328.81,"points":292,"is_member":true,"status":"CANCELLED","txn_date":"2026-02-10 21:10:07"}
{"txn_id":"TXN-64411","cust_id":1539140569,"amount":6380.8,"points":229,"is_member":false,"status":"CANCELLED","txn_date":"2026-02-10 10:37:31"}
{"txn_id":"TXN-69223","cust_id":6425597888,"amount":10109.23,"points":370,"is_member":true,"status":"COMPLETED","txn_date":"2026-02-10 11:30:42"}
{"txn_id":"TXN-71967","cust_id":7959785361,"amount":4286.21,"points":463,"is_member":true,"status":"PENDING","txn_date":"2026-02-10 12:40:53"}
{"txn_id":"TXN-74371","cust_id":6439968092,"amount":2075.31,"points":327,"is_member":false,"status":"COMPLETED","txn_date":"2026-02-10 14:50:14"}
{"txn_id":"TXN-77632","cust_id":6176871470,"amount":10738.02,"points":316,"is_member":false,"status":"CANCELLED","txn_date":"2026-02-10 09:52:11"}
{"txn_id":"TXN-80517","cust_id":4568329534,"amount":5052.38,"points":348,"is_member":false,"status":"COMPLETED","txn_date":"2026-02-10 22:31:05"}
{"txn_id":"TXN-83031","cust_id":1772578074,"points":219,"is_member":false,"status":"PENDING","txn_date":"2026-02-10 07:42:12"}
{"txn_id":"TXN-85462","cust_id":7245991553,"amount":4653.52,"points":350,"is_member":true,"status":"COMPLETED","txn_date":"2026-02-10 03:40:01"}
{"txn_id":"TXN-90727","cust_id":8913571312,"amount":3748.95,"points":353,"is_member":true,"status":"PENDING","txn_date":"2026-02-10 12:25:26"}
{"txn_id":"TXN-97233","cust_id":1474792354,"amount":5973.92,"points":34,"is_member":true,"status":"PENDING","txn_date":"2026-02-10 09:03:39"}
{"txn_id":"TXN-11334","cust_id":2213569454,"amount":445.72,"points":302,"is_member":true,"status":"CANCELLED","txn_date":"2026-02-10 01:12:50"}
{"txn_id":"TXN-13350","cust_id":6425597888,"amount":5582.22,"points":265,"is_member":true,"status":"CANCELLED","txn_date":"2026-02-10 19:05:03"}
{"txn_id":"TXN-15989","cust_id":6475869209,"amount":8324.51,"points":194,"is_member":false,"status":"CANCELLED","txn_date":"2026-02-10 04:49:05"}
{"txn_id":"TXN-18381","cust_id":1284364112,"amount":8500.0,"points":106,"is_member":true,"status":"COMPLETED","txn_date":"2026-02-10 12:43:05"}
{"txn_id":"TXN-22234","cust_id":1539140569,"amount":13012.7,"points":290,"is_member":false,"status":"PENDING","txn_date":"2026-02-10 10:36:41"}
{"txn_id":"TXN-25854","cust_id":2712293212,"amount":10865.57,"points":353,"is_member":true,"status":"CANCELLED","txn_date":"2026-02-10 02:15:35"}
{"txn_id":"TXN-30282","cust_id":9200954899,"amount":3649.57,"points":57,"is_member":true,"status":"CANCELLED","txn_date":"2026-02-10 21:44:21"}
{"txn_id":"TXN-33753","cust_id":7164848609,"amount":4260.45,"points":331,"is_member":true,"status":"CANCELLED","txn_date":"2026-02-10 08:56:44"}
{"txn_id":"TXN-35890","cust_id":6176871470,"amount":2846.82,"points":421,"is_member":true,"status":"PENDING","txn_date":"2026-02-10 18:05:07"}
{"txn_id":"TXN-41577","cust_id":5285552918,"amount":5985.71,"points":249,"is_member":true,"status":"PENDING","txn_date":"2026-02-10 16:06:51"}
{"txn_id":"TXN-46817","cust_id":7245991553,"amount":11441.69,"points":11,"is_member":true,"status":"COMPLETED","txn_date":"2026-02-10 21:53:35"}
{"txn_id":"TXN-52471","cust_id":3878529472,"amount":4571.53,"points":25,"is_member":true,"status":"COMPLETED","txn_date":"2026-02-10 01:11:02"}
{"txn_id":"TXN-54796","cust_id":5033983622,"amount":14468.33,"points":117,"is_member":false,"status":"COMPLETED","txn_date":"2026-02-10 18:23:18"}
{"txn_id":"TXN-58290","cust_id":9985810207,"amount":4162.77,"points":282,"is_member":true,"status":"COMPLETED","txn_date":"2026-02-10 10:53:07"}
{"txn_id":"TXN-64191","cust_id":9985810207,"amount":12383.16,"points":389,"is_member":false,"status":"PENDING","txn_date":"2026-02-10 06:59:31"}
{"txn_id":"TXN-66393","cust_id":2449494469,"amount":2534.26,"points":237,"is_member":true,"status":"PENDING","txn_date":"2026-02-10 06:50:36"}
{"txn_id":"TXN-68564","cust_id":7151155582,"amount":648.72,"points":493,"is_member":true,"status":"PENDING","txn_date":"2026-02-10 16:22:55"}
{"txn_id":"TXN-75699","cust_id":7651565215,"amount":14869.36,"points":395,"is_member":true,"status":"COMPLETED","txn_date":"2026-02-10 22:58:31"}
{"txn_id":"TXN-80922","cust_id":2712293212,"amount":9586.42,"points":393,"is_member":false,"status":"PENDING","txn_date":"2026-02-10 08:14:00"}
{"txn_id":"TXN-83423","cust_id":5630927942,"amount":1822.02,"points":305,"is_member":true,"status":"COMPLETED","txn_date":"2026-02-10 03:05:42"}
{"txn_id":"TXN-85533","cust_id":5105127221,"amount":9674.43,"points":131,"is_member":false,"status":"CANCELLED","txn_date":"2026-02-10 19:22:38"}
{"txn_id":"TXN-88072","cust_id":1539140569,"amount":843.4,"points":283,"is_member":false,"status":"COMPLETED","txn_date":"2026-02-10 12:30:19"}
{"txn_id":"TXN-90540","cust_id":3878529472,"amount":2191.24,"points":280,"is_member":false,"status":"CANCELLED","txn_date":"2026-02-10 21:32:34"}
{"txn_id":"TXN-93702","cust_id":4571629473,"amount":6750.45,"points":336,"is_member":true,"status":"CANCELLED","txn_date":"2026-02-10 03:42:35"}
{"txn_id":"TXN-97078","cust_id":6579398125,"amount":4944.16,"points":39,"is_member":false,"status":"COMPLETED","txn_date":"2026-02-10 22:10:02"}
{"txn_id":"TXN-12058","cust_id":7151155582,"amount":12980.27,"points":183,"is_member":true,"status":"PENDING","txn_date":"2026-02-10 21:28:50"}
{"txn_id":"TXN-18377","cust_id":8317563089,"points":66,"is_member":false,"status":"COMPLETED","txn_date":"2026-02-10 05:51:31"}
{"txn_id":"TXN-22996","cust_id":4351630478,"amount":14416.15,"points":29,"is_member":true,"status":"CANCELLED","txn_date":"2026-02-10 05:57:32"}
{"txn_id":"TXN-27365","cust_id":5630927942,"amount":13106.97,"points":239,"is_member":true,"status":"CANCELLED","txn_date":"2026-02-10 06:12:17"}
{"txn_id":"TXN-30279","cust_id":9985810207,"amount":7299.4,"points":49,"is_member":false,"status":"COMPLETED","txn_date":"2026-02-10 06:18:20"}
{"txn_id":"TXN-32262","cust_id":4312271815,"amount":1325.87,"points":55,"is_member":true,"status":"COMPLETED","txn_date":"2026-02-10 19:46:36"}
{"txn_id":"TXN-37001","cust_id":1284364112,"amount":9914.94,"points":499,"is_member":true,"status":"PENDING","txn_date":"2026-02-10 13:05:23"}
{"txn_id":"TXN-41235","cust_id":7651565215,"amount":12305.77,"points":209,"is_member":true,"status":"PENDING","txn_date":"2026-02-10 10:21:55"}
{"txn_id":"TXN-46434","cust_id":6759239331,"amount":6877.54,"points":361,"is_member":false,"status":"PENDING","txn_date":"2026-02-10 21:08:18"}
{"txn_id":"TXN-50561","cust_id":2542365134,"amount":12257.72,"points":431,"is_member":true,"status":"COMPLETED","txn_date":"2026-02-10 02:12:35"}
{"txn_id":"TXN-54996","cust_id":1474792354,"amount":13680.37,"points":196,"is_member":true,"status":"PENDING","txn_date":"2026-02-10 16:17:37"}
{"txn_id":"TXN-56146","cust_id":4571629473,"amount":5643.28,"points":253,"is_member":false,"status":"PENDING","txn_date":"2026-02-10 14:59:25"}
{"txn_id":"TXN-58964","cust_id":8317563089,"amount":13124.1,"points":238,"is_member":true,"status":"COMPLETED","txn_date":"2026-02-10 00:48:35"}
{"txn_id":"TXN-64075","cust_id":5630927942,"amount":1660.5,"points":101,"is_member":true,"status":"CANCELLED","txn_date":"2026-02-10 17:49:14"}
{"txn_id":"TXN-67191","cust_id":1474792354,"amount":6491.08,"points":255,"is_member":true,"status":"CANCELLED","txn_date":"2026-02-10 13:47:03"}
{"txn_id":"TXN-71424","cust_id":1539140569,"points":332,"is_member":false,"status":"COMPLETED","txn_date":"2026-02-10 08:02:36"}
{"txn_id":"TXN-75896","cust_id":2542365134,"amount":10504.56,"points":153,"is_member":false,"status":"CANCELLED","txn_date":"2026-02-10 23:15:17"}
{"txn_id":"TXN-77660","cust_id":6759239331,"amount":809.32,"points":167,"is_member":true,"status":"PENDING","txn_date":"2026-02-10 23:49:01"}
{"txn_id":"TXN-83400","cust_id":5033983622,"amount":11410.38,"points":475,"is_member":false,"status":"CANCELLED","txn_date":"2026-02-10 06:00:51"}
{"txn_id":"TXN-85619","cust_id":4568329534,"amount":464.11,"points":238,"is_member":false,"status":"COMPLETED","txn_date":"2026-02-10 13:17:21"}
{"txn_id":"TXN-87744","cust_id":7151155582,"amount":1345.39,"points":168,"is_member":true,"status":"PENDING","txn_date":"2026-02-10 00:45:40"}
{"txn_id":"TXN-89082","cust_id":7151155582,"amount":1212.76,"points":214,"is_member":true,"status":"CANCELLED","txn_date":"2026-02-10 06:12:01"}
{"txn_id":"TXN-90628","cust_id":6176871470,"amount":8095.13,"points":232,"is_member":false,"status":"COMPLETED","txn_date":"2026-02-10 04:36:46"}
{"txn_id":"TXN-93848","cust_id":1474792354,"amount":3167.71,"points":427,"is_member":false,"status":"PENDING","txn_date":"2026-02-10 06:05:36"}
{"txn_id":"TXN-97206","cust_id":7151155582,"amount":1061.01,"points":186,"is_member":false,"status":"COMPLETED","txn_date":"2026-02-10 20:52:38"}
{"txn_id":"TXN-10478","cust_id":3878529472,"amount":5644.13,"points":204,"is_member":false,"status":"COMPLETED","txn_date":"2026-02-10 11:14:08"}
{"txn_id":"TXN-15954","cust_id":4698594466,"amount":7539.78,"points":465,"is_member":true,"status":"PENDING","txn_date":"2026-02-10 01:05:50"}
{"txn_id":"TXN-18799","cust_id":8221048896,"amount":1208.11,"points":88,"is_member":true,"status":"COMPLETED","txn_date":"2026-02-10 10:08:28"}
{"txn_id":"TXN-21276","cust_id":6176871470,"amount":3054.57,"points":172,"is_member":false,"status":"PENDING","txn_date":"2026-02-10 18:35:51"}
{"txn_id":"TXN-24295","cust_id":1674513681,"points":431,"is_member":false,"status":"PENDING","txn_date":"2026-02-10 14:42:17"}
{"txn_id":"TXN-27412","cust_id":1971934265,"amount":3888.3,"points":125,"is_member":true,"status":"PENDING","txn_date":"2026-02-10 05:30:14"}
{"txn_id":"TXN-32087","cust_id":5630927942,"amount":8962.0,"points":208,"is_member":false,"status":"COMPLETED","txn_date":"2026-02-10 00:08:14"}
{"txn_id":"TXN-37155","cust_id":8317563089,"amount":11476.44,"points":324,"is_member":true,"status":"PENDING","txn_date":"2026-02-10 17:25:31"}
{"txn_id":"TXN-39681","cust_id":4312271815,"points":188,"is_member":false,"status":"COMPLETED","txn_date":"2026-02-10 18:13:59"}
{"txn_id":"TXN-42931","cust_id":5828340170,"amount":1317.47,"points":222,"is_member":true,"status":"PENDING","txn_date":"2026-02-10 23:52:31"}
{"txn_id":"TXN-44333","cust_id":6904500237,"amount":12463.29,"points":418,"is_member":true,"status":"CANCELLED","txn_date":"2026-02-10 13:40:12"}
{"txn_id":"TXN-49666","cust_id":1539140569,"amount":4729.72,"points":153,"is_member":true,"status":"COMPLETED","txn_date":"2026-02-10 03:10:40"}
{"txn_id":"TXN-52915","cust_id":5033983622,"amount":3604.9,"points":50,"is_member":true,"status":"COMPLETED","txn_date":"2026-02-10 09:18:09"}
{"txn_id":"TXN-59570","cust_id":1474792354,"points":237,"is_member":false,"status":"PENDING","txn_date":"2026-02-10 21:01:08"}
{"txn_id":"TXN-64608","cust_id":5285552918,"amount":2443.1,"points":310,"is_member":false,"status":"PENDING","txn_date":"2026-02-10 08:07:51"}
{"txn_id":"TXN-67285","cust_id":8871159003,"amount":7795.04,"points":332,"is_member":true,"status":"COMPLETED","txn_date":"2026-02-10 23:54:43"}
{"txn_id":"TXN-71060","cust_id":3878529472,"amount":5687.91,"points":68,"is_member":true,"status":"PENDING","txn_date":"2026-02-10 02:49:09"}
{"txn_id":"TXN-73264","cust_id":4312271815,"amount":7694.11,"points":217,"is_member":false,"status":"COMPLETED","txn_date":"2026-02-10 15:37:47"}
{"txn_id":"TXN-76257","cust_id":7164848609,"amount":4312.25,"points":162,"is_member":false,"status":"CANCELLED","txn_date":"2026-02-10 05:13:55"}
{"txn_id":"TXN-79979","cust_id":7151155582,"amount":11822.36,"points":136,"is_member":true,"status":"COMPLETED","txn_date":"2026-02-10 23:27:54"}
{"txn_id":"TXN-84982","cust_id":8148109337,"amount":12177.41,"points":335,"is_member":true,"status":"PENDING","txn_date":"2026-02-10 20:10:27"}
{"txn_id":"TXN-89583","cust_id":2449494469,"amount":2684.42,"points":288,"is_member":true,"status":"CANCELLED","txn_date":"2026-02-10 09:15:52"}
{"txn_id":"TXN-91312","cust_id":5285552918,"amount":7708.81,"points":299,"is_member":true,"status":"COMPLETED","txn_date":"2026-02-10 22:09:00"}
{"txn_id":"TXN-93701","cust_id":6904500237,"amount":4503.79,"points":80,"is_member":true,"status":"COMPLETED","txn_date":"2026-02-10 00:03:33"}
{"txn_id":"TXN-96991","cust_id":7164848609,"amount":13072.34,"points":169,"is_member":true,"status":"CANCELLED","txn_date":"2026-02-10 10:49:31"}
{"txn_id":"TXN-11848","cust_id":8317563089,"amount":545.08,"points":279,"is_member":true,"status":"CANCELLED","txn_date":"2026-02-10 23:17:45"}
{"txn_id":"TXN-17363","cust_id":7151155582,"amount":3495.33,"points":136,"is_member":false,"status":"PENDING","txn_date":"2026-02-10 03:21:01"}
{"txn_id":"TXN-18843","cust_id":2213569454,"amount":11971.42,"points":351,"is_member":true,"status":"COMPLETED","txn_date":"2026-02-10 08:41:29"}
{"txn_id":"TXN-20917","cust_id":9985810207,"amount":6252.52,"points":382,"is_member":false,"status":"COMPLETED","txn_date":"2026-02-10 20:19:19"}
{"txn_id":"TXN-21733","cust_id":6579398125,"amount":11085.76,"points":90,"is_member":true,"status":"CANCELLED","txn_date":"2026-02-10 20:39:16"}
{"txn_id":"TXN-24967","cust_id":1674513681,"points":419,"is_member":false,"status":"CANCELLED","txn_date":"2026-02-10 13:09:14"}
{"txn_id":"TXN-31847","cust_id":4474717052,"amount":1819.6,"points":466,"is_member":true,"status":"COMPLETED","txn_date":"2026-02-10 14:16:07"}
{"txn_id":"TXN-40005","cust_id":2542365134,"amount":3699.67,"points":272,"is_member":false,"status":"CANCELLED","txn_date":"2026-02-10 05:07:25"}
{"txn_id":"TXN-43576","cust_id":5630927942,"amount":13939.32,"points":413,"is_member":true,"status":"COMPLETED","txn_date":"2026-02-10 07:52:15"}
{"txn_id":"TXN-45307","cust_id":6579398125,"amount":8718.42,"points":29,"is_member":false,"status":"CANCELLED","txn_date":"2026-02-10 04:05:36"}
{"txn_id":"TXN-49559","cust_id":7151155582,"amount":9806.73,"points":459,"is_member":true,"status":"COMPLETED","txn_date":"2026-02-10 01:45:57"}
{"txn_id":"TXN-52811","cust_id":3991308074,"amount":11488.98,"points":379,"is_member":false,"status":"CANCELLED","txn_date":"2026-02-10 16:13:23"}
{"txn_id":"TXN-57530","cust_id":2712293212,"amount":7523.18,"points":36,"is_member":false,"status":"COMPLETED","txn_date":"2026-02-10 17:30:41"}
{"txn_id":"TXN-62673","cust_id":5828340170,"amount":11011.25,"points":282,"is_member":false,"status":"COMPLETED","txn_date":"2026-02-10 16:54:31"}
{"txn_id":"TXN-64560","cust_id":2542365134,"amount":3988.69,"points":483,"is_member":true,"status":"COMPLETED","txn_date":"2026-02-10 16:07:41"}
{"txn_id":"TXN-67780","cust_id":6475869209,"amount":1151.65,"points":462,"is_member":true,"status":"CANCELLED","txn_date":"2026-02-10 08:30:05"}
{"txn_id":"TXN-70021","cust_id":4571629473,"amount":6430.39,"points":125,"is_member":true,"status":"PENDING","txn_date":"2026-02-10 09:34:52"}
{"txn_id":"TXN-73924","cust_id":2542365134,"amount":3033.47,"points":153,"is_member":false,"status":"COMPLETED","txn_date":"2026-02-10 14:46:37"}
{"txn_id":"TXN-75484","cust_id":8019249439,"amount":2797.93,"points":401,"is_member":true,"status":"COMPLETED","txn_date":"2026-02-10 12:28:42"}
{"txn_id":"TXN-84335","cust_id":4568329534,"amount":6904.08,"points":283,"is_member":true,"status":"PENDING","txn_date":"2026-02-10 23:02:12"}
{"txn_id":"TXN-86386","cust_id":3991308074,"amount":5853.39,"points":13,"is_member":false,"status":"CANCELLED","txn_date":"2026-02-10 08:25:59"}
{"txn_id":"TXN-90645","cust_id":5747456772,"amount":9058.32,"points":297,"is_member":false,"status":"COMPLETED","txn_date":"2026-02-10 20:25:54"}
{"txn_id":"TXN-92315","cust_id":8716952983,"amount":13179.97,"points":492,"is_member":true,"status":"CANCELLED","txn_date":"2026-02-10 04:29:29"}
{"txn_id":"TXN-95232","cust_id":5747456772,"amount":5176.78,"points":411,"is_member":false,"status":"PENDING","txn_date":"2026-02-10 17:44:42"}
{"txn_id":"TXN-99008","cust_id":9985810207,"amount":11167.84,"points":432,"is_member":true,"status":"PENDING","txn_date":"2026-02-10 12:13:08"}
{"txn_id":"TXN-19904","cust_id":1971934265,"amount":14717.16,"points":74,"is_member":true,"status":"PENDING","txn_date":"2026-02-10 18:18:22"}
{"txn_id":"TXN-22942","cust_id":6737382526,"amount":14037.75,"points":386,"is_member":true,"status":"CANCELLED","txn_date":"2026-02-10 16:03:40"}
{"txn_id":"TXN-27626","cust_id":5105127221,"amount":2337.73,"points":389,"is_member":true,"status":"COMPLETED","txn_date":"2026-02-10 16:20:06"}
{"txn_id":"TXN-30570","cust_id":2542365134,"amount":1623.23,"points":499,"is_member":true,"status":"PENDING","txn_date":"2026-02-10 19:19:10"}
{"txn_id":"TXN-33022","cust_id":6176871470,"points":388,"is_member":false,"status":"PENDING","txn_date":"2026-02-10 20:58:27"}
{"txn_id":"TXN-36379","cust_id":7651565215,"amount":7720.0,"points":41,"is_member":false,"status":"PENDING","txn_date":"2026-02-10 08:10:33"}
{"txn_id":"TXN-37866","cust_id":4474717052,"amount":9750.33,"points":99,"is_member":true,"status":"CANCELLED","txn_date":"2026-02-10 07:02:15"}
{"txn_id":"TXN-40206","cust_id":7245991553,"amount":8436.94,"points":2,"is_member":true,"status":"COMPLETED","txn_date":"2026-02-10 21:24:12"}
{"txn_id":"TXN-46724","cust_id":4568329534,"amount":14472.57,"points":69,"is_member":false,"status":"PENDING","txn_date":"2026-02-10 08:40:44"}
{"txn_id":"TXN-50580","cust_id":6737382526,"amount":9889.8,"points":111,"is_member":false,"status":"COMPLETED","txn_date":"2026-02-10 01:18:33"}
{"txn_id":"TXN-53737","cust_id":5105127221,"amount":3542.4,"points":310,"is_member":true,"status":"PENDING","txn_date":"2026-02-10 12:30:31"}
{"txn_id":"TXN-56504","cust_id":3127368181,"amount":2231.78,"points":494,"is_member":false,"status":"COMPLETED","txn_date":"2026-02-10 16:52:43"}
{"txn_id":"TXN-62856","cust_id":6904500237,"amount":4716.44,"points":238,"is_member":false,"status":"COMPLETED","txn_date":"2026-02-10 11:21:18"}
{"txn_id":"TXN-65101","cust_id":1211827224,"amount":14391.64,"points":67,"is_member":false,"status":"COMPLETED","txn_date":"2026-02-10 14:25:16"}
{"txn_id":"TXN-69455","cust_id":6904500237,"amount":4925.25,"points":160,"is_member":true,"status":"COMPLETED","txn_date":"2026-02-10 04:19:29"}
{"txn_id":"TXN-72976","cust_id":8148109337,"amount":13740.68,"points":462,"is_member":true,"status":"COMPLETED","txn_date":"2026-02-10 18:08:15"}
{"txn_id":"TXN-74957","cust_id":8221048896,"amount":8920.48,"points":361,"is_member":false,"status":"PENDING","txn_date":"2026-02-10 04:05:10"}
{"txn_id":"TXN-77907","cust_id":5395716639,"amount":12453.67,"points":125,"is_member":true,"status":"PENDING","txn_date":"2026-02-10 03:05:01"}
{"txn_id":"TXN-82002","cust_id":6439968092,"amount":6709.77,"points":137,"is_member":true,"status":"PENDING","txn_date":"2026-02-10 12:27:19"}
{"txn_id":"TXN-83088","cust_id":5105127221,"amount":14294.47,"points":281,"is_member":true,"status":"COMPLETED","txn_date":"2026-02-10 08:08:53"}
{"txn_id":"TXN-88841","cust_id":8317563089,"amount":7450.07,"points":27,"is_member":false,"status":"CANCELLED","txn_date":"2026-02-10 00:20:07"}
{"txn_id":"TXN-90422","cust_id":8871159003,"points":34,"is_member":false,"status":"CANCELLED","txn_date":"2026-02-10 13:06:46"}
{"txn_id":"TXN-92819","cust_id":9985810207,"amount":6392.94,"points":113,"is_member":false,"status":"COMPLETED","txn_date":"2026-02-10 09:05:09"}
{"txn_id":"TXN-95934","cust_id":4571629473,"amount":1706.66,"points":308,"is_member":false,"status":"COMPLETED","txn_date":"2026-02-10 15:07:19"}
{"txn_id":"TXN-98239","cust_id":1772578074,"amount":8972.63,"points":67,"is_member":true,"status":"PENDING","txn_date":"2026-02-10 07:36:21"}
{"txn_id":"TXN-13321","cust_id":3127368181,"amount":13468.14,"points":93,"is_member":true,"status":"CANCELLED","txn_date":"2026-02-10 08:43:22"}
{"txn_id":"TXN-20341","cust_id":5828340170,"amount":13669.01,"points":458,"is_member":true,"status":"CANCELLED","txn_date":"2026-02-10 19:45:51"}
{"txn_id":"TXN-22434","cust_id":4058611172,"amount":4995.36,"points":316,"is_member":true,"status":"COMPLETED","txn_date":"2026-02-10 06:19:48"}
{"txn_id":"TXN-24319","cust_id":6904500237,"amount":7359.8,"points":59,"is_member":true,"status":"COMPLETED","txn_date":"2026-02-10 07:57:42"}
{"txn_id":"TXN-25898","cust_id":5285552918,"amount":9989.05,"points":94,"is_member":true,"status":"CANCELLED","txn_date":"2026-02-10 15:24:24"}
{"txn_id":"TXN-28120","cust_id":4058611172,"amount":6460.34,"points":229,"is_member":true,"status":"COMPLETED","txn_date":"2026-02-10 12:28:25"}
{"txn_id":"TXN-30164","cust_id":8716952983,"amount":8544.38,"points":98,"is_member":false,"status":"PENDING","txn_date":"2026-02-10 19:58:29"}
{"txn_id":"TXN-31809","cust_id":9200954899,"amount":10761.31,"points":51,"is_member":true,"status":"CANCELLED","txn_date":"2026-02-10 18:58:25"}
{"txn_id":"TXN-36409","cust_id":8019249439,"amount":3491.17,"points":174,"is_member":true,"status":"PENDING","txn_date":"2026-02-10 09:48:40"}
{"txn_id":"TXN-38856","cust_id":5828340170,"amount":11605.68,"points":242,"is_member":false,"status":"PENDING","txn_date":"2026-02-10 23:40:41"}
{"txn_id":"TXN-43427","cust_id":7164848609,"points":265,"is_member":false,"status":"COMPLETED","txn_date":"2026-02-10 09:38:54"}
{"txn_id":"TXN-46090","cust_id":5630927942,"amount":10131.6,"points":458,"is_member":false,"status":"CANCELLED","txn_date":"2026-02-10 08:38:35"}
{"txn_id":"TXN-53132","cust_id":2213569454,"amount":4050.0,"points":168,"is_member":true,"status":"COMPLETED","txn_date":"2026-02-10 19:44:04"}
{"txn_id":"TXN-57201","cust_id":7164848609,"amount":10987.35,"points":489,"is_member":true,"status":"CANCELLED","txn_date":"2026-02-10 18:44:10"}
{"txn_id":"TXN-58521","cust_id":7651565215,"amount":202.68,"points":478,"is_member":true,"status":"PENDING","txn_date":"2026-02-10 10:29:34"}
{"txn_id":"TXN-61982","cust_id":8221048896,"amount":14719.2,"points":12,"is_member":true,"status":"PENDING","txn_date":"2026-02-10 05:46:43"}
{"txn_id":"TXN-65368","cust_id":5033983622,"amount":10639.97,"points":223,"is_member":false,"status":"PENDING","txn_date":"2026-02-10 03:02:08"}
{"txn_id":"TXN-69044","cust_id":4351630478,"amount":10076.35,"points":155,"is_member":true,"status":"COMPLETED","txn_date":"2026-02-10 21:27:22"}
{"txn_id":"TXN-73972","cust_id":4351630478,"amount":8802.98,"points":456,"is_member":false,"status":"PENDING","txn_date":"2026-02-10 11:21:34"}
{"txn_id":"TXN-81451","cust_id":6176871470,"amount":9573.91,"points":176,"is_member":false,"status":"COMPLETED","txn_date":"2026-02-10 08:21:40"}
{"txn_id":"TXN-84622","cust_id":7151155582,"amount":9569.8,"points":425,"is_member":true,"status":"COMPLETED","txn_date":"2026-02-10 01:53:06"}
{"txn_id":"TXN-89925","cust_id":3991308074,"amount":5636.68,"points":291,"is_member":false,"status":"COMPLETED","txn_date":"2026-02-10 06:25:12"}
{"txn_id":"TXN-92565","cust_id":4312271815,"points":162,"is_member":true,"status":"COMPLETED","txn_date":"2026-02-10 01:51:43"}
{"txn_id":"TXN-95804","cust_id":1211827224,"amount":8644.45,"points":366,"is_member":true,"status":"PENDING","txn_date":"2026-02-10 17:05:35"}
{"txn_id":"TXN-99201","cust_id":6425597888,"amount":14914.25,"points":211,"is_member":true,"status":"COMPLETED","txn_date":"2026-02-10 09:05:08"}
